dashboard/__init__.py
dashboard/admin.py
dashboard/apps.py
dashboard/forms.py
dashboard/models.py
dashboard/tests.py
dashboard/urls.py
dashboard/views.py
dashboard/management/__init__.py
dashboard/management/commands/__init__.py
dashboard/management/commands/create_missing_profiles.py
dashboard/migrations/0001_initial.py
dashboard/migrations/__init__.py
dashboard/static/dashboard/js/components.js
dashboard/static/dashboard/js/main.js
dashboard/templates/dashboard/base.html
dashboard/templates/dashboard/home.html
dashboard/templates/dashboard/auth/auth_base.html
dashboard/templates/dashboard/auth/login.html
dashboard/templates/dashboard/auth/password_change.html
dashboard/templates/dashboard/auth/password_change_done.html
dashboard/templates/dashboard/auth/password_reset.html
dashboard/templates/dashboard/auth/password_reset_complete.html
dashboard/templates/dashboard/auth/password_reset_confirm.html
dashboard/templates/dashboard/auth/password_reset_done.html
dashboard/templates/dashboard/auth/password_reset_email.html
dashboard/templates/dashboard/auth/password_reset_subject.txt
dashboard/templates/dashboard/auth/profile.html
dashboard/templates/dashboard/auth/register.html
dashboard/templates/dashboard/components/chart.html
dashboard/templates/dashboard/components/data_table.html
dashboard/templates/dashboard/components/form_field.html
dashboard/templates/dashboard/components/modal.html
dashboard/templates/dashboard/components/navbar.html
dashboard/templates/dashboard/components/sidebar.html
dashboard/templates/dashboard/components/toast.html
dashboard/tests/__init__.py
dashboard/tests/test_auth.py
dashboard/tests/test_components.py
dashproj/__init__.py
dashproj/asgi.py
dashproj/settings.py
dashproj/urls.py
dashproj/wsgi.py
tests/__init__.py
tests/settings.py
tests/urls.py
django_dashboard_boilerplate-0.1.0.dist-info/LICENSE
django_dashboard_boilerplate-0.1.0.dist-info/METADATA
django_dashboard_boilerplate-0.1.0.dist-info/WHEEL
django_dashboard_boilerplate-0.1.0.dist-info/top_level.txt
django_dashboard_boilerplate-0.1.0.dist-info/RECORD
