Metadata-Version: 2.1
Name: django-dashboard-boilerplate
Version: 0.1.0
Summary: A reusable dashboard boilerplate for Django applications with modern UI and authentication
Home-page: https://github.com/dttsi/django-dashboard-boilerplate
Author: dttsi
Author-email: dttsi@example.com
Classifier: Programming Language :: Python :: 3
Classifier: License :: OSI Approved :: MIT License
Classifier: Operating System :: OS Independent
Classifier: Framework :: Django
Classifier: Framework :: Django :: 4.2
Requires-Python: >=3.6
License-File: LICENSE
Requires-Dist: django >=3.2
Requires-Dist: pillow >=8.0.0
Provides-Extra: dev
Requires-Dist: pytest >=7.0.0 ; extra == 'dev'
Requires-Dist: pytest-django >=4.5.0 ; extra == 'dev'
Requires-Dist: coverage >=6.0.0 ; extra == 'dev'
Requires-Dist: black >=22.0.0 ; extra == 'dev'
Requires-Dist: isort >=5.0.0 ; extra == 'dev'
Requires-Dist: flake8 >=4.0.0 ; extra == 'dev'
